Workbook
Name BSCheck: Model!$F$119
Name L_Scenarios: Scenarios!$D$12:$D$14
Name million: Inp!$F$12
Name S_Scenarios: Scenarios!$E$11
Name ScenarioUSed: Scenarios!$D$11

Sheet Cover
C7: CTD Industries
C8: ="Financial Model for "&$D$14+1&" to "&$D$14+5 -> Financial Model for 2021 to 2025
C11: Modeller | D11: Animashaun Jafar
C12: Version | D12: Ver 1.01
C13: Circularity in Model | D13: Net Interest Expense Line of the P&L
C14: Base Year | D14: =Hist!I7 -> 2020

Sheet Hist
B2: CTD Industries
B3: Income Statement
B5: ($ Millions)
G7: 2018 | H7: 2019 | I7: 2020
B9: Revenue Growth | H9: =H13/G13-1 -> 0.10350333 | I9: =I13/H13-1 -> 0.086390331
B10: COGS (% of revenue) | G10: =G15/G13 -> 0.71735387 | H10: =H15/H13 -> 0.72797685 | I10: =I15/I13 -> 0.72829834
B11: SG&A (% of revenue) | G11: =G16/G13 -> 0.16261232 | H11: =H16/H13 -> 0.15453797 | I11: =I16/I13 -> 0.1496135
C13: Revenue | G13: 3194.1 | H13: 3524.7 | I13: 3829.2
C15: Cost of Sales | G15: 2291.3 | H15: 2565.9 | I15: 2788.8
C16: SG&A | G16: 519.4 | H16: 544.7 | I16: 572.9
C17: Total Costs | G17: =SUM(G15:G16) -> 2810.7 | H17: =SUM(H15:H16) -> 3110.6 | I17: =SUM(I15:I16) -> 3361.7
C19: Cost Adjustments - (Gain) / Loss | G19: -7 | H19: -4.2 | I19: 76
C20: EBITDA | G20: =G13-G17-G19 -> 390.4 | H20: =H13-H17-H19 -> 418.3 | I20: =I13-I17-I19 -> 391.5
C22: Depreciation & Amortization | G22: 95.1 | H22: 113.2 | I22: 126.2
C23: EBIT | G23: =G20-G22 -> 295.3 | H23: =H20-H22 -> 305.1 | I23: =I20-I22 -> 265.3
C25: Cost Adjustments - (Gain) / Loss | G25: 116 | H25: 123.9 | I25: 105.8
C26: Net Interest Expense | G26: 62 | H26: 56.6 | I26: 59.1
C27: EBT | G27: =G23-G25-G26 -> 117.3 | H27: =H23-H25-H26 -> 124.6 | I27: =I23-I25-I26 -> 100.4
C29: Current Taxes | G29: 40.5 | H29: 22.7 | I29: 24.8
C30: Deferred Income Taxes | G30: 16.9 | H30: 31.7 | I30: 24
C31: Total Income Taxes | G31: =SUM(G29:G30) -> 57.4 | H31: =SUM(H29:H30) -> 54.4 | I31: =SUM(I29:I30) -> 48.8
C33: Net Income | G33: =G27-G31 -> 59.9 | H33: =H27-H31 -> 70.2 | I33: =I27-I31 -> 51.6
C35: Preferred Dividend | G35: 0.544 | H35: 0.544 | I35: 0.544
C36: Net Income to Common | G36: =G33-G35 -> 59.356 | H36: =H33-H35 -> 69.656 | I36: =I33-I35 -> 51.056
B41: CTD Industries
B42: Cash Flow Statement
B44: ($ Millions)
G46: 2018 | H46: 2019 | I46: 2020
B48: Operating Activities
C49: Net Income | G49: 59.9 | H49: 70.2 | I49: 51.6
C50: Depreciation | G50: 95.1 | H50: 113.2 | I50: 126.2
C51: Deferred Income Taxes | G51: 16.9 | H51: 31.7 | I51: 24
C52: Changes in Working Capital | G52: -119 | H52: -4.5 | I52: -83.8
C53: Other | G53: 161.9 | H53: 164.2 | I53: 242.1
C54: Operating Cash Flow | G54: =SUM(G49:G53) -> 214.8 | H54: =SUM(H49:H53) -> 374.8 | I54: =SUM(I49:I53) -> 360.1
B57: Investing Activities
C58: CAPEX | G58: -134.4 | H58: -158.7 | I58: -194.1
C59: Asset Disposal | G59: 2 | H59: 3.4 | I59: 10.5
C60: Other | G60: -14.9 | H60: -11.3 | I60: -15.4
C61: Investing Cash Flow | G61: =SUM(G58:G60) -> -147.3 | H61: =SUM(H58:H60) -> -166.6 | I61: =SUM(I58:I60) -> -199
B64: Financing Activities
C65: Revolver Issuance / (Repayment) | G65: 10.3 | H65: =H105-G105 -> 589.5 | I65: =I105-H105 -> -200
C66: Variable Rate Long Term Debt Issue / (Repayment) | G66: 0 | H66: 0 | I66: 0
C67: Fixed Rate Long Term Debt Issue / (Repayment) | G67: -259.3 | H67: 4.7 | I67: -10
C68: Preferred Share Issuance/ (Buy-Back) | G68: 0 | H68: 0 | I68: 0
C69: Common Share Issuance/ (Buy-Back) | G69: 300.2 | H69: 0.5 | I69: -94
C70: Preferred Share Dividends | G70: -0.544 | H70: -0.544 | I70: -0.544
C71: Common Share Dividends | G71: -483 | H71: 0 | I71: 0
C72: Other | G72: -102.7 | H72: -46.3 | I72: -54.1
C73: Financing Cash Flow | G73: =SUM(G65:G72) -> -535.044 | H73: =SUM(H65:H72) -> 547.856 | I73: =SUM(I65:I72) -> -358.644
C75: Change in Cash Position | G75: =G54+G61+G73 -> -467.544 | H75: =H54+H61+H73 -> 756.056 | I75: =I54+I61+I73 -> -197.544
C76: Beginning Cash | G76: 542.4 | H76: =G77 -> 74.856 | I76: =H77 -> 830.912
C77: Ending Cash | G77: =G76+G75 -> 74.856 | H77: =H76+H75 -> 830.912 | I77: =I76+I75 -> 633.368
B81: CTD Industries
B82: Balance Sheet
B85: ($ Millions)
G86: 2018 | H86: 2019 | I86: 2020
B87: ASSETS
C88: Cash and Equivalents | G88: =G77 -> 74.856 | H88: =H77 -> 830.912 | I88: =I77 -> 633.368
C89: Accounts Receivable | G89: 266.6 | H89: 306.8 | I89: 308.4
C90: Inventory | G90: 532.7 | H90: 630.2 | I90: 685.9
C91: Other | G91: 51.4 | H91: 61 | I91: 65.3
C92: Total Current Assets | G92: =SUM(G88:G91) -> 925.556 | H92: =SUM(H88:H91) -> 1828.912 | I92: =SUM(I88:I91) -> 1692.968
C94: Net PP&E | G94: 515.3 | H94: 586.9 | I94: 636.6
C95: Goodwill | G95: 116 | H95: 115.9 | I95: 116
C96: Intangibles | G96: 219.9 | H96: 220.6 | I96: 207.9
C97: Deferred income taxes | G97: 14 | H97: 17.7 | I97: 28.8
C98: Other | G98: 145.9 | H98: 159.1 | I98: 132.5
C99: Total Long Term Assets | G99: =SUM(G94:G98) -> 1011.1 | H99: =SUM(H94:H98) -> 1100.2 | I99: =SUM(I94:I98) -> 1121.8
C101: Total Assets | G101: =G92+G99 -> 1936.656 | H101: =H92+H99 -> 2929.112 | I101: =I92+I99 -> 2814.768
B104: LIABILITIES AND EQUITY
C105: Bank Debt - Revolver | G105: 10.5 | H105: 600 | I105: 400
C106: Accounts Payable | G106: 547 | H106: 678.4 | I106: 650.3
C107: Other | G107: 206.6 | H107: 248.5 | I107: 266.2
C108: Total Current Liabilities | G108: =SUM(G105:G107) -> 764.1 | H108: =SUM(H105:H107) -> 1526.9 | I108: =SUM(I105:I107) -> 1316.5
C110: Variable Rate Long Term Debt | G110: 0 | H110: 0 | I110: 250
C111: Fixed Rate Long Term Debt | G111: 889.9 | H111: 1035.5 | I111: 896.6
C112: Other | G112: 324 | H112: 394.7 | I112: 367.4
C113: Total Long Term Liabilities | G113: =SUM(G110:G112) -> 1213.9 | H113: =SUM(H110:H112) -> 1430.2 | I113: =SUM(I110:I112) -> 1514
C115: Total Liabilities | G115: =G108+G113 -> 1978 | H115: =H108+H113 -> 2957.1 | I115: =I108+I113 -> 2830.5
C117: Preferred Shares | G117: 6.4 | H117: 6.4 | I117: 6.4
C118: Common Shares | G118: 365.3 | H118: 371.9 | I118: 346.4
C119: Retained Earnings | G119: -429.244 | H119: -419.888 | I119: -395.232
C120: Other | G120: 16.2 | H120: 13.6 | I120: 26.7
C121: Shareholder's Equity | G121: =SUM(G117:G120) -> -41.344 | H121: =SUM(H117:H120) -> -27.988 | I121: =SUM(I117:I120) -> -15.732
B123: Total Liabilities and Equity | G123: =G115+G121 -> 1936.656 | H123: =H115+H121 -> 2929.112 | I123: =I115+I121 -> 2814.768

Sheet Summary
B2: =Cover!$C$7 -> CTD Industries | I2: ="Financial Forecast: "&L6&" to "&P6 -> Financial Forecast: 2021 to 2025
B3: Summary | I3: =IF(BSCheck=0,"BS Check: OK","BS Check: ERROR") -> BS Check: OK | K3: =ScenarioUSed -> Scenario: Worst Case
I5: Actual | J5: Actual | K5: Actual | L5: Forecast | M5: Forecast | N5: Forecast | O5: Forecast | P5: Forecast
E6: Units | F6: Trend | I6: =Hist!G7 -> 2018 | J6: =Hist!H7 -> 2019 | K6: =Hist!I7 -> 2020 | L6: =K6+1 -> 2021 | M6: =L6+1 -> 2022 | N6: =M6+1 -> 2023 | O6: =N6+1 -> 2024 | P6: =O6+1 -> 2025
B8: Analysis Based on : Base Case Scenario
C10: Revenue
D11: Gross Revenue | E11: $'m | I11: 3194.1 | J11: 3524.7 | K11: 3829.2 | L11: 4025.012 | M11: 4231.2989 | N11: 4448.6336 | O11: 4370.7679 | P11: 4480.0371
D12: Growth Rate | E12: % | J12: 0.10350333 | K12: 0.086390331 | L12: 0.051136536 | M12: 0.05125125 | N12: 0.05136359 | O12: -0.01750329 | P12: 0.025
C13: EBITDA
D14: EBITDA | E14: $'m | I14: 390.4 | J14: 418.3 | K14: 391.5 | L14: 544.1017 | M14: 658.35656 | N14: 780.68444 | O14: 669.17896 | P14: 704.41638
D15: Growth Rate | E15: % | J15: 0.071465164 | K15: -0.06406885 | L15: 0.38978724 | M15: 0.20998805 | N15: 0.18580795 | O15: -0.14283041 | P15: 0.052657691
D16: EBITA Margin | E16: % | I16: 0.12222535 | J16: 0.11867677 | K16: 0.10224068 | L16: 0.13518014 | M16: 0.15559207 | N16: 0.17548859 | O16: 0.15310329 | P16: 0.1572345
C17: Net Profit
D18: Net Profit | E18: $'m | I18: 291.9 | J18: 318 | K18: 263.2 | L18: 242.33499 | M18: 318.794 | N18: 395.32477 | O18: 307.91855 | P18: 322.95339
D19: Growth Rate | E19: % | J19: 0.089414183 | K19: -0.17232704 | L19: -0.07927434 | M19: 0.31550956 | N19: 0.2400634 | O19: -0.22109978 | P19: 0.048827325
D20: Net Profit Margin | E20: % | I20: 0.091387245 | J20: 0.090220444 | K20: 0.068734984 | L20: 0.060207272 | M20: 0.075341877 | N20: 0.088864313 | O20: 0.070449531 | P20: 0.072087213
C21: Dupont Analysis
D22: ROE | E22: % | I22: -7.0602748 | J22: -11.362012 | K22: -16.730231 | L22: 2.8306444 | M22: 0.7960422 | N22: 0.51627727 | O22: 0.29075246 | P22: 0.23794516
D23: Net Profit Margin | E23: % | I23: 0.091387245 | J23: 0.090220444 | K23: 0.068734984 | L23: 0.060207272 | M23: 0.075341877 | N23: 0.088864313 | O23: 0.070449531 | P23: 0.072087213
D24: Asset Turnover | E24: times | I24: 1.6492862 | J24: 1.203334 | K24: 1.3603963 | L24: 1.6862288 | M24: 1.6399473 | N24: 1.6011196 | O24: 1.5019726 | P24: 1.4678268
D25: Financial Leverage | E25: times | I25: -46.842492 | J25: -104.656 | K25: -178.91991 | L25: 27.88174 | M25: 6.4427277 | N25: 3.6285393 | O25: 2.7477883 | P25: 2.2487637
B27: Analysis Based on : Best Case Scenario
C29: Revenue
D30: Gross Revenue | E30: $'m | I30: 3194.1 | J30: 3524.7 | K30: 3829.2 | L30: 4100.8391 | M30: 4392.3949 | N30: 4705.3557 | O30: 4556.6786 | P30: 4719.5228
D31: Growth Rate | E31: % | J31: 0.10350333 | K31: 0.086390331 | L31: 0.070938859 | M31: 0.071096629 | N31: 0.071250599 | O31: -0.031597415 | P31: 0.035737471
C32: EBITDA
D33: EBITDA | E33: $'m | I33: 390.4 | J33: 418.3 | K33: 391.5 | L33: 626.90076 | M33: 836.46737 | N33: 1064.5477 | O33: 923.98549 | P33: 1032.3393
D34: Growth Rate | E34: % | J34: 0.071465164 | K34: -0.06406885 | L34: 0.60127908 | M34: 0.33428992 | N34: 0.27267097 | O34: -0.1320394 | P34: 0.11726783
D35: EBITA Margin | E35: % | I35: 0.12222535 | J35: 0.11867677 | K35: 0.10224068 | L35: 0.15287134 | M35: 0.19043537 | N35: 0.22624171 | O35: 0.20277609 | P35: 0.21873806
C36: Net Profit
D37: Net Profit | E37: $'m | I37: 291.9 | J37: 318 | K37: 263.2 | L37: 300.72437 | M37: 445.03993 | N37: 596.52168 | O37: 489.61766 | P37: 556.9981
D38: Growth Rate | E38: % | J38: 0.089414183 | K38: -0.17232704 | L38: 0.14256978 | M38: 0.47989317 | N38: 0.34037787 | O38: -0.17921229 | P38: 0.13761848
D39: Net Profit Margin | E39: % | I39: 0.091387245 | J39: 0.090220444 | K39: 0.068734984 | L39: 0.073332399 | M39: 0.10132056 | N39: 0.12677504 | O39: 0.10745056 | P39: 0.11802001
C40: Dupont Analysis
D41: ROE | E41: % | I41: -7.0602748 | J41: -11.362012 | K41: -16.730231 | L41: 2.3239317 | M41: 0.82575331 | N41: 0.56537195 | O41: 0.32977799 | P41: 0.28440881
D42: Net Profit Margin | E42: % | I42: 0.091387245 | J42: 0.090220444 | K42: 0.068734984 | L42: 0.073332399 | M42: 0.10132056 | N42: 0.12677504 | O42: 0.10745056 | P42: 0.11802001
D43: Asset Turnover | E43: times | I43: 1.6492862 | J43: 1.203334 | K43: 1.3603963 | L43: 1.7027742 | M43: 1.6470672 | N43: 1.5515038 | O43: 1.3897034 | P43: 1.3127772
D44: Financial Leverage | E44: times | I44: -46.842492 | J44: -104.656 | K44: -178.91991 | L44: 18.61103 | M44: 4.9481335 | N44: 2.8744029 | O44: 2.2084668 | P44: 1.8356775
B47: Analysis Based on : Worst Case Scenario
C49: Revenue
D50: Gross Revenue | E50: $'m | I50: 3194.1 | J50: 3524.7 | K50: 3829.2 | L50: 3933.2369 | M50: 4040.2997 | N50: 4150.4786 | O50: 4120.4797 | P50: 4161.6845
D51: Growth Rate | E51: % | J51: 0.10350333 | K51: 0.086390331 | L51: 0.027169367 | M51: 0.027220025 | N51: 0.02726998 | O51: -0.0072278271 | P51: 0.01
C52: EBITDA
D53: EBITDA | E53: $'m | I53: 390.4 | J53: 418.3 | K53: 391.5 | L53: 431.41062 | M53: 418.32958 | N53: 403.99681 | O53: 278.17021 | P53: 204.10572
D54: Growth Rate | E54: % | J54: 0.071465164 | K54: -0.06406885 | L54: 0.10194284 | M54: -0.030321545 | N54: -0.03426191 | O54: -0.31145444 | P54: -0.266256
D55: EBITA Margin | E55: % | I55: 0.12222535 | J55: 0.11867677 | K55: 0.10224068 | L55: 0.10968335 | M55: 0.10353924 | N55: 0.097337403 | O55: 0.067509181 | P55: 0.049044017
C56: Net Profit
D57: Net Profit | E57: $'m | I57: 291.9 | J57: 318 | K57: 263.2 | L57: 162.51082 | M57: 146.69451 | N57: 121.77828 | O57: 16.731712 | P57: -53.829585
D58: Growth Rate | E58: % | J58: 0.089414183 | K58: -0.17232704 | L58: -0.38255767 | M58: -0.09732464 | N58: -0.16985118 | O58: -0.86260512 | P58: -4.2172192
D59: Net Profit Margin | E59: % | I59: 0.091387245 | J59: 0.090220444 | K59: 0.068734984 | L59: 0.041317323 | M59: 0.03630783 | N59: 0.029340779 | O59: 0.0040606223 | P59: -0.012934566
C60: Dupont Analysis
D61: ROE | E61: % | I61: -7.0602748 | J61: -11.362012 | K61: -16.730231 | L61: 6.3127874 | M61: 0.69348943 | N61: 0.3276964 | O61: 0.037469053 | P61: -0.11646892
D62: Net Profit Margin | E62: % | I62: 0.091387245 | J62: 0.090220444 | K62: 0.068734984 | L62: 0.041317323 | M62: 0.03630783 | N62: 0.029340779 | O62: 0.0040606223 | P62: -0.012934566
D63: Asset Turnover | E63: times | I63: 1.6492862 | J63: 1.203334 | K63: 1.3603963 | L63: 1.6490331 | M63: 1.5683224 | N63: 1.4972826 | O63: 1.4098413 | P63: 1.3562231
D64: Financial Leverage | E64: times | I64: -46.842492 | J64: -104.656 | K64: -178.91991 | L64: 92.653029 | M64: 12.178792 | N64: 7.4592687 | O64: 6.5450036 | P64: 6.6393725
A66: Summary Generator:
B67: ="Analysis Based on : "&INDEX(L_Scenarios,S_Scenarios)&" Scenario" -> Analysis Based on : Worst Case Scenario
C69: Revenue
D70: =Model!D12 -> Revenue | E70: $'m | I70: =Model!I12 -> 3194.1 | J70: =Model!J12 -> 3524.7 | K70: =Model!K12 -> 3829.2 | L70: =Model!L12 -> 3933.2369 | M70: =Model!M12 -> 4040.2997 | N70: =Model!N12 -> 4150.4786 | O70: =Model!O12 -> 4120.4797 | P70: =Model!P12 -> 4161.6845
D71: Growth Rate | E71: % | J71: =J70/I70-1 -> 0.10350333 | K71: =K70/J70-1 -> 0.086390331 | L71: =L70/K70-1 -> 0.027169367 | M71: =M70/L70-1 -> 0.027220025 | N71: =N70/M70-1 -> 0.02726998 | O71: =O70/N70-1 -> -0.0072278271 | P71: =P70/O70-1 -> 0.01
C72: EBITDA
D73: =Model!D19 -> EBITDA | E73: $'m | I73: =Model!I19 -> 390.4 | J73: =Model!J19 -> 418.3 | K73: =Model!K19 -> 391.5 | L73: =Model!L19 -> 431.41062 | M73: =Model!M19 -> 418.32958 | N73: =Model!N19 -> 403.99681 | O73: =Model!O19 -> 278.17021 | P73: =Model!P19 -> 204.10572
D74: Growth Rate | E74: % | J74: =J73/I73-1 -> 0.071465164 | K74: =K73/J73-1 -> -0.06406885 | L74: =L73/K73-1 -> 0.10194284 | M74: =M73/L73-1 -> -0.030321545 | N74: =N73/M73-1 -> -0.03426191 | O74: =O73/N73-1 -> -0.31145444 | P74: =P73/O73-1 -> -0.266256
D75: =Model!D37 -> EBITA Margin | E75: % | I75: =Model!I37 -> 0.12222535 | J75: =Model!J37 -> 0.11867677 | K75: =Model!K37 -> 0.10224068 | L75: =Model!L37 -> 0.10968335 | M75: =Model!M37 -> 0.10353924 | N75: =Model!N37 -> 0.097337403 | O75: =Model!O37 -> 0.067509181 | P75: =Model!P37 -> 0.049044017
C76: Net Profit
D77: Net Profit | E77: $'m | I77: =Model!I32 -> 291.9 | J77: =Model!J32 -> 318 | K77: =Model!K32 -> 263.2 | L77: =Model!L32 -> 175.01214 | M77: =Model!M32 -> 159.86359 | N77: =Model!N32 -> 135.24174 | O77: =Model!O32 -> 30.408067 | P77: =Model!P32 -> -40.202446
D78: Growth Rate | E78: % | J78: =J77/I77-1 -> 0.089414183 | K78: =K77/J77-1 -> -0.17232704 | L78: =L77/K77-1 -> -0.33506026 | M78: =M77/L77-1 -> -0.086557108 | N78: =N77/M77-1 -> -0.1540179 | O78: =O77/N77-1 -> -0.77515767 | P78: =P77/O77-1 -> -2.322098
D79: =Model!D40 -> Net Profit Margin | E79: % | I79: =Model!I40 -> 0.091387245 | J79: =Model!J40 -> 0.090220444 | K79: =Model!K40 -> 0.068734984 | L79: =Model!L40 -> 0.044495702 | M79: =Model!M40 -> 0.039567261 | N79: =Model!N40 -> 0.032584613 | O79: =Model!O40 -> 0.0073797396 | P79: =Model!P40 -> -0.0096601378
C80: Dupont Analysis
D81: =Model!D39 -> ROE | E81: % | I81: =Model!I39 -> -7.0602748 | J81: =Model!J39 -> -11.362012 | K81: =Model!K39 -> -16.730231 | L81: =Model!L39 -> 5.0027618 | M81: =Model!M39 -> 0.69737317 | N81: =Model!N39 -> 0.34180084 | O81: =Model!O39 -> 0.06401885 | P81: =Model!P39 -> -0.083271133
D82: =Model!D40 -> Net Profit Margin | E82: % | I82: =Model!I40 -> 0.091387245 | J82: =Model!J40 -> 0.090220444 | K82: =Model!K40 -> 0.068734984 | L82: =Model!L40 -> 0.044495702 | M82: =Model!M40 -> 0.039567261 | N82: =Model!N40 -> 0.032584613 | O82: =Model!O40 -> 0.0073797396 | P82: =Model!P40 -> -0.0096601378
D83: =Model!D41 -> Asset Turnover | E83: times | I83: =Model!I41 -> 1.6492862 | J83: =Model!J41 -> 1.203334 | K83: =Model!K41 -> 1.3603963 | L83: =Model!L41 -> 1.6604926 | M83: =Model!M41 -> 1.5787388 | N83: =Model!N41 -> 1.5068242 | O83: =Model!O41 -> 1.4184588 | P83: =Model!P41 -> 1.3643265
D84: =Model!D42 -> Financial Leverage | E84: times | I84: =Model!I42 -> -46.842492 | J84: =Model!J42 -> -104.656 | K84: =Model!K42 -> -178.91991 | L84: =Model!L42 -> 67.710314 | M84: =Model!M42 -> 11.163978 | N84: =Model!N42 -> 6.9614221 | O84: =Model!O42 -> 6.1157553 | P84: =Model!P42 -> 6.3181922

Sheet Inp
B2: =Cover!$C$7 -> CTD Industries | I2: ="Financial Forecast: "&L6&" to "&P6 -> Financial Forecast: 2021 to 2025
B3: Inputs & Assumptions | I3: =IF(BSCheck=0,"BS Check: OK","BS Check: ERROR") -> BS Check: OK | K3: =ScenarioUSed -> Scenario: Worst Case
I5: Actual | J5: Actual | K5: Actual | L5: Forecast | M5: Forecast | N5: Forecast | O5: Forecast | P5: Forecast
E6: Units | F6: Inputs | I6: =Hist!G7 -> 2018 | J6: =Hist!H7 -> 2019 | K6: =Hist!I7 -> 2020 | L6: =K6+1 -> 2021 | M6: =L6+1 -> 2022 | N6: =M6+1 -> 2023 | O6: =N6+1 -> 2024 | P6: =O6+1 -> 2025
B9: General Assumptions
D11: Days in the Year | I11: =DATE(I6,12,31)-DATE(I6,1,1)+1 -> 365 | J11: =DATE(J6,12,31)-DATE(J6,1,1)+1 -> 365 | K11: =DATE(K6,12,31)-DATE(K6,1,1)+1 -> 366 | L11: =DATE(L6,12,31)-DATE(L6,1,1)+1 -> 365 | M11: =DATE(M6,12,31)-DATE(M6,1,1)+1 -> 365 | N11: =DATE(N6,12,31)-DATE(N6,1,1)+1 -> 365 | O11: =DATE(O6,12,31)-DATE(O6,1,1)+1 -> 366 | P11: =DATE(P6,12,31)-DATE(P6,1,1)+1 -> 365
D12: Millions | E12: Constant | F12: 1000000
C14: Style Guide
D16: Number | E16: Number | F16: 1234.5
D17: Input | E17: Number
D18: Percent | E18: Percent | F18: 0.23
D19: Multiples | E19: Number | F19: 12.5
D20: Linked Cell | E20: Number
D21: Units | E21: Text | F21: Text
D22: Headings 1 | E22: Text | F22: TEXT
D23: Headings 2 | E23: Text | F23: Text
D24: Headings 3 | E24: Text | F24: Text
B26: Revenue Assumptions
C28: Core Revenue Assumptions
D30: Total Sales | E30: $'m | K30: =Hist!I13 -> 3829.2 | L30: ="<<"&_xlfn.FORMULATEXT(K30) -> <<=Hist!I13
D31: Auxillary Sales | E31: $'m | K31: 574.5
D32: Industrial Monitor Sales | E32: $'m | K32: =K30-K31 -> 3254.7 | L32: ="<<"&_xlfn.FORMULATEXT(K32) -> <<=K30-K31
D33: Average Unit Sales Price | E33: $ | K33: 14105
D34: Quantity of Industrial Monitors Sold | E34: units | K34: =K32*million/K33 -> 230747.96 | L34: ="<<"&_xlfn.FORMULATEXT(K34) -> <<=K32*million/K33
D35: Volume capacity | E35: units | L35: 260000 | M35: 260000 | N35: 260000 | O35: 240000 | P35: 240000
D37: Increase in Average Sales Price per Device | E37: % | K37: =_xlfn.FORMULATEXT(L37)&" >>" -> =Scenarios!L33 >> | L37: =Scenarios!L33 -> 0.01 | M37: =Scenarios!M33 -> 0.01 | N37: =Scenarios!N33 -> 0.01 | O37: =Scenarios!O33 -> 0.01 | P37: =Scenarios!P33 -> 0.01
D38: Volume Growth Rate in Devices | E38: units | K38: =_xlfn.FORMULATEXT(L38)&" >>" -> =Scenarios!L19 >> | L38: =Scenarios!L19 -> 0.02 | M38: =Scenarios!M19 -> 0.02 | N38: =Scenarios!N19 -> 0.02 | O38: =Scenarios!O19 -> 0.02 | P38: =Scenarios!P19 -> 0.02
D39: =Scenarios!B24 -> Auxiliary Business YoY Sales Growth | E39: % | K39: =_xlfn.FORMULATEXT(L39)&" >>" -> =Scenarios!L26 >> | L39: =Scenarios!L26 -> 0.01 | M39: =Scenarios!M26 -> 0.01 | N39: =Scenarios!N26 -> 0.01 | O39: =Scenarios!O26 -> 0.01 | P39: =Scenarios!P26 -> 0.01
D41: Additional Devices | E41: units | K41: =K34 -> 230747.96 | L41: =K41*(1+L38) -> 235362.92 | M41: =L41*(1+M38) -> 240070.18 | N41: =M41*(1+N38) -> 244871.58 | O41: =N41*(1+O38) -> 249769.01 | P41: =O41*(1+P38) -> 254764.39
B43: Production Cost Assumptions
D45: Cost of Sales | E45: $'m | K45: =Hist!I15 -> 2788.8 | L45: ="<<"&_xlfn.FORMULATEXT(K45) -> <<=Hist!I15
D46: Variable Cost | E46: $'m | K46: 0.25
D47: Fixed Cost | E47: $'m | K47: =1-K46 -> 0.75 | L47: ="<<"&_xlfn.FORMULATEXT(K47) -> <<=1-K46
D48: Variable cost per Device | E48: $ | K48: =K45*K46*million/K34 -> 3021.4785 | L48: ="<<"&_xlfn.FORMULATEXT(K48) -> <<=K45*K46*million/K34
D49: Fixed Cost | E49: $'m | K49: =K45*K47 -> 2091.6 | L49: ="<<"&_xlfn.FORMULATEXT(K49) -> <<=K45*K47
D51: SG& A | E51: $'m | L51: 615
D53: Cost inflation | E53: % | K53: =_xlfn.FORMULATEXT(L53)&" >>" -> =Scenarios!L40 >> | L53: =Scenarios!L40 -> 0.03 | M53: =Scenarios!M40 -> 0.03 | N53: =Scenarios!N40 -> 0.03 | O53: =Scenarios!O40 -> 0.03 | P53: =Scenarios!P40 -> 0.03
B56: Capex & Depreciation Assumptions
C58: Capex (Tangible Assets)
D59: Additions | E59: $'m | L59: 225 | M59: 250 | N59: 275 | O59: 275 | P59: 275
D60: Depreciation Method | E60: Straight Line
C62: Useful Life of Assets (Tangible)
D63: Remaining Assets | E63: Years | F63: 9
D64: New Assets | E64: Years | F64: 15
C66: Capex (Intangible Assets)
D67: Additions | E67: $'m | L67: 40 | M67: 40 | N67: 40 | O67: 40 | P67: 40
D68: Amortization Method | E68: Straight Line
C70: Useful Life of Assets (Intangible)
D71: Remaining Assets | E71: Years | F71: 5
D72: New Assets | E72: Years | F72: 10
B75: Working Capital Assumptions
D77: Days in the Year | E77: Days | I77: =I11 -> 365 | J77: =J11 -> 365 | K77: =K11 -> 366 | L77: ="<<"&_xlfn.FORMULATEXT(K77) -> <<=K11
C79: Extract from Financials
D80: Revenue | E80: $'m | I80: =Hist!G13 -> 3194.1 | J80: =Hist!H13 -> 3524.7 | K80: =Hist!I13 -> 3829.2 | L80: ="<<"&_xlfn.FORMULATEXT(K80) -> <<=Hist!I13
D81: Cost of Sales | E81: $'m | I81: =Hist!G15 -> 2291.3 | J81: =Hist!H15 -> 2565.9 | K81: =Hist!I15 -> 2788.8 | L81: ="<<"&_xlfn.FORMULATEXT(K81) -> <<=Hist!I15
C83: Balances
D84: =Hist!C89 -> Accounts Receivable | E84: $'m | I84: =Hist!G89 -> 266.6 | J84: =Hist!H89 -> 306.8 | K84: =Hist!I89 -> 308.4 | L84: ="<<"&_xlfn.FORMULATEXT(K84) -> <<=Hist!I89
D85: =Hist!C90 -> Inventory | E85: $'m | I85: =Hist!G90 -> 532.7 | J85: =Hist!H90 -> 630.2 | K85: =Hist!I90 -> 685.9 | L85: ="<<"&_xlfn.FORMULATEXT(K85) -> <<=Hist!I90
D86: Other Assets | E86: $'m | I86: =Hist!G91 -> 51.4 | J86: =Hist!H91 -> 61 | K86: =Hist!I91 -> 65.3 | L86: ="<<"&_xlfn.FORMULATEXT(K86) -> <<=Hist!I91
D87: =Hist!C106 -> Accounts Payable | E87: $'m | I87: =Hist!G106 -> 547 | J87: =Hist!H106 -> 678.4 | K87: =Hist!I106 -> 650.3 | L87: ="<<"&_xlfn.FORMULATEXT(K87) -> <<=Hist!I106
D88: Other Liabilities | E88: $'m | I88: =Hist!G107 -> 206.6 | J88: =Hist!H107 -> 248.5 | K88: =Hist!I107 -> 266.2 | L88: ="<<"&_xlfn.FORMULATEXT(K88) -> <<=Hist!I107
C90: Days
D91: =D84 -> Accounts Receivable | E91: Days | H91: =_xlfn.FORMULATEXT(I91)&" >>" -> =I84/I80*I$77 >> | I91: =I84/I80*I$77 -> 30.465233 | J91: =J84/J80*J$77 -> 31.770647 | K91: =K84/K80*K$77 -> 29.47728 | L91: 29.5 | M91: 29.5 | N91: 29.5 | O91: 29.5 | P91: 29.5
D92: =D85 -> Inventory | E92: Days | H92: =_xlfn.FORMULATEXT(I92)&" >>" -> =I85/I$81*I$77 >> | I92: =I85/I$81*I$77 -> 84.858159 | J92: =J85/J$81*J$77 -> 89.646128 | K92: =K85/K$81*K$77 -> 90.016997 | L92: 90 | M92: 90 | N92: 90 | O92: 90 | P92: 90
D93: =D86 -> Other Assets | E93: Days | H93: =_xlfn.FORMULATEXT(I93)&" >>" -> =I86/I$81*I$77 >> | I93: =I86/I$81*I$77 -> 8.1879283 | J93: =J86/J$81*J$77 -> 8.6772672 | K93: =K86/K$81*K$77 -> 8.5699225 | L93: 8.6 | M93: 8.6 | N93: 8.6 | O93: 8.6 | P93: 8.6
D94: =D87 -> Accounts Payable | E94: Days | H94: =_xlfn.FORMULATEXT(I94)&" >>" -> =I87/I$81*I$77 >> | I94: =I87/I$81*I$77 -> 87.136124 | J94: =J87/J$81*J$77 -> 96.502592 | K94: =K87/K$81*K$77 -> 85.34488 | L94: 85.3 | M94: 85.3 | N94: 85.3 | O94: 85.3 | P94: 85.3
D95: =D88 -> Other Liabilities | E95: Days | H95: =_xlfn.FORMULATEXT(I95)&" >>" -> =I88/I$81*I$77 >> | I95: =I88/I$81*I$77 -> 32.911011 | J95: =J88/J$81*J$77 -> 35.349195 | K95: =K88/K$81*K$77 -> 34.935886 | L95: 34.9 | M95: 34.9 | N95: 34.9 | O95: 34.9 | P95: 34.9
B98: Taxation Assumptions
D100: Company Tax Rate | E100: % | F100: 0.3
D102: Incremental in EBT due to timing Diff | E102: $'m | L102: 20 | M102: 20 | N102: 20 | O102: 20 | P102: 20
B105: Debt & Interest Rate Assumptions
C107: Interest rates
D108: Excess Cash | E108: % | F108: 0.01 | L108: =$F108 -> 0.01 | M108: =$F108 -> 0.01 | N108: =$F108 -> 0.01 | O108: =$F108 -> 0.01 | P108: =$F108 -> 0.01
D109: Fixed Rate Senior Secured Debt | E109: % | F109: 0.0525 | L109: =$F109 -> 0.0525 | M109: =$F109 -> 0.0525 | N109: =$F109 -> 0.0525 | O109: =$F109 -> 0.0525 | P109: =$F109 -> 0.0525
D110: Revolver | E110: % | F110: 0.0525 | L110: =$F110 -> 0.0525 | M110: =$F110 -> 0.0525 | N110: =$F110 -> 0.0525 | O110: =$F110 -> 0.0525 | P110: =$F110 -> 0.0525
D112: LIBOR | E112: % | L112: 0.011 | M112: 0.011 | N112: 0.011 | O112: 0.011 | P112: 0.011
D113: Premium on Variable Rate Term Debt | E113: % | L113: 0.0225 | M113: 0.0225 | N113: 0.0225 | O113: 0.0225 | P113: 0.0225
C115: Debt Repayment
D116: Amortisation on Fixed Senior secured Debt | E116: $'m | L116: 150 | M116: 150 | N116: 150 | O116: 150 | P116: 150
D117: Amortisation on Variable Senior secured Debt | E117: $'m | L117: 25 | M117: 25 | N117: 25 | O117: 25 | P117: 25
D119: Company will draw on Revolver if it needs to through a cash sweep & Debt Amortising payments occur in the middle of the year
B121: Equity Assumptions
C123: Common Shares
D124: Common Share Issuance / (Buy-Back) | E124: $'m | L124: -80 | M124: -40 | N124: -20 | O124: -20 | P124: -20
D126: Stock Price | E126: $ | F126: 5
D127: Dividend Pay-out Ratio | E127: % | L127: 0.25 | M127: 0.25 | N127: 0.25 | O127: 0.25 | P127: 0.25
C129: Common Shares
D130: Preferred Share Issuance / (Buy-Back) | E130: $'m | M130: 120 | N130: 100 | O130: 100 | P130: 100
D131: Dividend Pay-out Ratio | E131: % | L131: 0.085 | M131: 0.085 | N131: 0.085 | O131: 0.085 | P131: 0.085
B133: Other Assumptions
D135: Cost inflation | E135: % | L135: =Scenarios!L40 -> 0.03 | M135: =Scenarios!M40 -> 0.03 | N135: =Scenarios!N40 -> 0.03 | O135: =Scenarios!O40 -> 0.03 | P135: =Scenarios!P40 -> 0.03
D137: Cost Adjustments (from Operations) - Gain/(Loss) | E137: $'m | L137: 0 | M137: 0 | N137: 0 | O137: 0 | P137: 0
D138: Cost Adjustments (from Financing) - Gain/(Loss) | E138: $'m | L138: 0 | M138: 0 | N138: 0 | O138: 0 | P138: 0
D140: Change in Goodwill: Addition / (impairement) | E140: $'m | L140: 0 | M140: 0 | N140: 0 | O140: 0 | P140: 0
D141: Change in Other Equity: Additions / (Reduction) | E141: $'m | L141: 0 | M141: 0 | N141: 0 | O141: 0 | P141: 0
D142: Change in Other Operating Activities: Additions / (Reduction) | E142: $'m | L142: 0 | M142: 0 | N142: 0 | O142: 0 | P142: 0
D143: Change in Other Investing Activities: Additions / (Reduction) | E143: $'m | L143: 0 | M143: 0 | N143: 0 | O143: 0 | P143: 0
D144: Change in Other Financing Activities: Additions / (Reduction) | E144: $'m | L144: 0 | M144: 0 | N144: 0 | O144: 0 | P144: 0
D146: Cash Reserve Requirements | E146: $'m | L146: 0 | M146: 0 | N146: 0 | O146: 0 | P146: 0
D147: Minimum cash balance for all forecast years

Sheet Scenarios
B2: =Cover!$C$7 -> CTD Industries | I2: ="Financial Forecast: "&L6&" to "&P6 -> Financial Forecast: 2021 to 2025
B3: Scenario Analysis | I3: =IF(BSCheck=0,"BS Check: OK","BS Check: ERROR") -> BS Check: OK | K3: =ScenarioUSed -> Scenario: Worst Case
I5: Actual | J5: Actual | K5: Actual | L5: Forecast | M5: Forecast | N5: Forecast | O5: Forecast | P5: Forecast
E6: Units | F6: Inputs | I6: =Hist!G7 -> 2018 | J6: =Hist!H7 -> 2019 | K6: =Hist!I7 -> 2020 | L6: =K6+1 -> 2021 | M6: =L6+1 -> 2022 | N6: =M6+1 -> 2023 | O6: =N6+1 -> 2024 | P6: =O6+1 -> 2025
B9: Scenario Used
D11: ="Scenario: "&INDEX(L_Scenarios,S_Scenarios) -> Scenario: Worst Case | E11: 3
D12: Base Case
D13: Best Case
D14: Worst Case
B17: Core Business: Volume Growth
D19: Used in the Model | E19: Units | L19: =INDEX(L20:L22,S_Scenarios) -> 0.02 | M19: =INDEX(M20:M22,S_Scenarios) -> 0.02 | N19: =INDEX(N20:N22,S_Scenarios) -> 0.02 | O19: =INDEX(O20:O22,S_Scenarios) -> 0.02 | P19: =INDEX(P20:P22,S_Scenarios) -> 0.02
D20: =D$12 -> Base Case | E20: Units | L20: 0.03 | M20: 0.03 | N20: 0.03 | O20: 0.03 | P20: 0.03
D21: =D$13 -> Best Case | E21: Units | L21: 0.04 | M21: 0.04 | N21: 0.04 | O21: 0.04 | P21: 0.04
D22: =D$14 -> Worst Case | E22: Units | L22: 0.02 | M22: 0.02 | N22: 0.02 | O22: 0.02 | P22: 0.02
B24: Auxiliary Business YoY Sales Growth
D26: Used in the Model | E26: Units | L26: =INDEX(L27:L29,S_Scenarios) -> 0.01 | M26: =INDEX(M27:M29,S_Scenarios) -> 0.01 | N26: =INDEX(N27:N29,S_Scenarios) -> 0.01 | O26: =INDEX(O27:O29,S_Scenarios) -> 0.01 | P26: =INDEX(P27:P29,S_Scenarios) -> 0.01
D27: =D$12 -> Base Case | E27: Units | L27: 0.025 | M27: 0.025 | N27: 0.025 | O27: 0.025 | P27: 0.025
D28: =D$13 -> Best Case | E28: Units | L28: 0.04 | M28: 0.04 | N28: 0.04 | O28: 0.04 | P28: 0.04
D29: =D$14 -> Worst Case | E29: Units | L29: 0.01 | M29: 0.01 | N29: 0.01 | O29: 0.01 | P29: 0.01
B31: Core Business: Sales Price Inflation Scenarios
D33: Used in the Model | E33: % | L33: =INDEX(L34:L36,S_Scenarios) -> 0.01 | M33: =INDEX(M34:M36,S_Scenarios) -> 0.01 | N33: =INDEX(N34:N36,S_Scenarios) -> 0.01 | O33: =INDEX(O34:O36,S_Scenarios) -> 0.01 | P33: =INDEX(P34:P36,S_Scenarios) -> 0.01
D34: Base Case | E34: % | L34: 0.025 | M34: 0.025 | N34: 0.025 | O34: 0.025 | P34: 0.025
D35: Best Case | E35: % | L35: 0.035 | M35: 0.035 | N35: 0.035 | O35: 0.035 | P35: 0.035
D36: Worst Case | E36: % | L36: 0.01 | M36: 0.01 | N36: 0.01 | O36: 0.01 | P36: 0.01
B38: Cost Inflation Scenario
D40: Used in the Model | E40: % | L40: =INDEX(L41:L43,S_Scenarios) -> 0.03 | M40: =INDEX(M41:M43,S_Scenarios) -> 0.03 | N40: =INDEX(N41:N43,S_Scenarios) -> 0.03 | O40: =INDEX(O41:O43,S_Scenarios) -> 0.03 | P40: =INDEX(P41:P43,S_Scenarios) -> 0.03
D41: Base Case | E41: % | L41: 0.02 | M41: 0.02 | N41: 0.02 | O41: 0.02 | P41: 0.02
D42: Best Case | E42: % | L42: 0.015 | M42: 0.015 | N42: 0.015 | O42: 0.015 | P42: 0.015
D43: Worst Case | E43: % | L43: 0.03 | M43: 0.03 | N43: 0.03 | O43: 0.03 | P43: 0.03

Sheet Model
B2: =Cover!$C$7 -> CTD Industries | I2: ="Financial Forecast: "&L6&" to "&P6 -> Financial Forecast: 2021 to 2025
B3: Model & Schedules | I3: =IF(BSCheck=0,"BS Check: OK","BS Check: ERROR") -> BS Check: OK | K3: =ScenarioUSed -> Scenario: Worst Case
I5: Actual | J5: Actual | K5: Actual | L5: Forecast | M5: Forecast | N5: Forecast | O5: Forecast | P5: Forecast | Q5: Formula in
E6: Units | F6: Inputs | I6: =Hist!G7 -> 2018 | J6: =Hist!H7 -> 2019 | K6: =Hist!I7 -> 2020 | L6: =K6+1 -> 2021 | M6: =L6+1 -> 2022 | N6: =M6+1 -> 2023 | O6: =N6+1 -> 2024 | P6: =O6+1 -> 2025 | Q6: =L6 -> 2021
A8: FINANCIAL STATEMENTS
B10: Income Statement
D12: =Hist!C13 -> Revenue | E12: $'m | I12: =Hist!G13 -> 3194.1 | J12: =Hist!H13 -> 3524.7 | K12: =Hist!I13 -> 3829.2 | L12: =L143 -> 3933.2369 | M12: =M143 -> 4040.2997 | N12: =N143 -> 4150.4786 | O12: =O143 -> 4120.4797 | P12: =P143 -> 4161.6845 | Q12: =_xlfn.FORMULATEXT(L12) -> =L143
D14: =Hist!C15 -> Cost of Sales | E14: $'m | I14: =Hist!G15 -> 2291.3 | J14: =Hist!H15 -> 2565.9 | K14: =Hist!I15 -> 2788.8 | L14: =L160 -> 2886.8263 | M14: =M160 -> 2988.5202 | N14: =N160 -> 3094.0283 | O14: =O160 -> 3170.2824 | P14: =P160 -> 3265.3909 | Q14: =_xlfn.FORMULATEXT(L14) -> =L160
D15: =Hist!C16 -> SG&A | E15: $'m | I15: =Hist!G16 -> 519.4 | J15: =Hist!H16 -> 544.7 | K15: =Hist!I16 -> 572.9 | L15: =L162 -> 615 | M15: =M162 -> 633.45 | N15: =N162 -> 652.4535 | O15: =O162 -> 672.02711 | P15: =P162 -> 692.18792 | Q15: =_xlfn.FORMULATEXT(L15) -> =L162
D16: =Hist!C17 -> Total Costs | E16: $'m | I16: =SUM(I14:I15) -> 2810.7 | J16: =SUM(J14:J15) -> 3110.6 | K16: =SUM(K14:K15) -> 3361.7 | L16: =SUM(L14:L15) -> 3501.8263 | M16: =SUM(M14:M15) -> 3621.9702 | N16: =SUM(N14:N15) -> 3746.4818 | O16: =SUM(O14:O15) -> 3842.3095 | P16: =SUM(P14:P15) -> 3957.5788 | Q16: =_xlfn.FORMULATEXT(L16) -> =SUM(L14:L15)
D18: =Hist!C19 -> Cost Adjustments - (Gain) / Loss | E18: $'m | I18: =Hist!G19 -> -7 | J18: =Hist!H19 -> -4.2 | K18: =Hist!I19 -> 76 | L18: =Inp!L137 -> 0 | M18: =Inp!M137 -> 0 | N18: =Inp!N137 -> 0 | O18: =Inp!O137 -> 0 | P18: =Inp!P137 -> 0 | Q18: =_xlfn.FORMULATEXT(L18) -> =Inp!L137
D19: =Hist!C20 -> EBITDA | E19: $'m | I19: =I12-I16-I18 -> 390.4 | J19: =J12-J16-J18 -> 418.3 | K19: =K12-K16-K18 -> 391.5 | L19: =L12-L16+L18 -> 431.41062 | M19: =M12-M16+M18 -> 418.32958 | N19: =N12-N16+N18 -> 403.99681 | O19: =O12-O16+O18 -> 278.17021 | P19: =P12-P16+P18 -> 204.10572 | Q19: =_xlfn.FORMULATEXT(L19) -> =L12-L16+L18
D21: =Hist!C22 -> Depreciation & Amortization | E21: $'m | I21: =Hist!G22 -> 95.1 | J21: =Hist!H22 -> 113.2 | K21: =Hist!I22 -> 126.2 | L21: =L200 -> 121.81333 | M21: =M200 -> 141.64667 | N21: =N200 -> 163.14667 | O21: =O200 -> 185.48 | P21: =P200 -> 207.81333 | Q21: =_xlfn.FORMULATEXT(L21) -> =L200
D22: =Hist!C23 -> EBIT | E22: $'m | I22: =I19-I21 -> 295.3 | J22: =J19-J21 -> 305.1 | K22: =K19-K21 -> 265.3 | L22: =L19-L21 -> 309.59729 | M22: =M19-M21 -> 276.68292 | N22: =N19-N21 -> 240.85015 | O22: =O19-O21 -> 92.690212 | P22: =P19-P21 -> -3.7076095 | Q22: =_xlfn.FORMULATEXT(L22) -> =L19-L21
D24: =Hist!C25 -> Cost Adjustments - (Gain) / Loss | E24: $'m | I24: =Hist!G25 -> 116 | J24: =Hist!H25 -> 123.9 | K24: =Hist!I25 -> 105.8 | L24: =Inp!L138 -> 0 | M24: =Inp!M138 -> 0 | N24: =Inp!N138 -> 0 | O24: =Inp!O138 -> 0 | P24: =Inp!P138 -> 0 | Q24: =_xlfn.FORMULATEXT(L24) -> =Inp!L138
D25: =Hist!C26 -> Net Interest Expense | E25: $'m | I25: =Hist!G26 -> 62 | J25: =Hist!H26 -> 56.6 | K25: =Hist!I26 -> 59.1 | L25: =L342 -> 59.579945 | M25: =M342 -> 48.306353 | N25: =N342 -> 47.647661 | O25: =O342 -> 49.250115 | P25: =P342 -> 53.724456 | Q25: =_xlfn.FORMULATEXT(L25) -> =L342
D26: =Hist!C27 -> EBT | E26: $'m | I26: =I22+I24-I25 -> 349.3 | J26: =J22+J24-J25 -> 372.4 | K26: =K22+K24-K25 -> 312 | L26: =L22+L24-L25 -> 250.01734 | M26: =M22+M24-M25 -> 228.37656 | N26: =N22+N24-N25 -> 193.20249 | O26: =O22+O24-O25 -> 43.440096 | P26: =P22+P24-P25 -> -57.432066 | Q26: =_xlfn.FORMULATEXT(L26) -> =L22+L24-L25
D28: =Hist!C29 -> Current Taxes | E28: $'m | I28: =Hist!G29 -> 40.5 | J28: =Hist!H29 -> 22.7 | K28: =Hist!I29 -> 24.8 | L28: =L228 -> 81.005203 | M28: =M228 -> 74.512969 | N28: =N228 -> 63.960746 | O28: =O228 -> 19.032029 | P28: =P228 -> -11.22962 | Q28: =_xlfn.FORMULATEXT(L28) -> =L228
D29: =Hist!C30 -> Deferred Income Taxes | E29: $'m | I29: =Hist!G30 -> 16.9 | J29: =Hist!H30 -> 31.7 | K29: =Hist!I30 -> 24 | L29: =-L229 -> -6 | M29: =-M229 -> -6 | N29: =-N229 -> -6 | O29: =-O229 -> -6 | P29: =-P229 -> -6 | Q29: =_xlfn.FORMULATEXT(L29) -> =-L229
D30: =Hist!C31 -> Total Income Taxes | E30: $'m | I30: =SUM(I28:I29) -> 57.4 | J30: =SUM(J28:J29) -> 54.4 | K30: =SUM(K28:K29) -> 48.8 | L30: =SUM(L28:L29) -> 75.005203 | M30: =SUM(M28:M29) -> 68.512969 | N30: =SUM(N28:N29) -> 57.960746 | O30: =SUM(O28:O29) -> 13.032029 | P30: =SUM(P28:P29) -> -17.22962 | Q30: =_xlfn.FORMULATEXT(L30) -> =SUM(L28:L29)
D32: =Hist!C33 -> Net Income | E32: $'m | I32: =I26-I30 -> 291.9 | J32: =J26-J30 -> 318 | K32: =K26-K30 -> 263.2 | L32: =L26-L30 -> 175.01214 | M32: =M26-M30 -> 159.86359 | N32: =N26-N30 -> 135.24174 | O32: =O26-O30 -> 30.408067 | P32: =P26-P30 -> -40.202446 | Q32: =_xlfn.FORMULATEXT(L32) -> =L26-L30
D34: Preferred Dividends | E34: $'m | I34: =Hist!G35 -> 0.544 | J34: =Hist!H35 -> 0.544 | K34: =Hist!I35 -> 0.544 | L34: =L279 -> 0.544 | M34: =M279 -> 5.644 | N34: =N279 -> 14.994 | O34: =O279 -> 23.494 | P34: =P279 -> 31.994 | Q34: =_xlfn.FORMULATEXT(L34) -> =L279
D35: Net Income to Common | E35: $'m | I35: =I32-I34 -> 291.356 | J35: =J32-J34 -> 317.456 | K35: =K32-K34 -> 262.656 | L35: =L32-L34 -> 174.46814 | M35: =M32-M34 -> 154.21959 | N35: =N32-N34 -> 120.24774 | O35: =O32-O34 -> 6.9140672 | P35: =P32-P34 -> -72.196446 | Q35: =_xlfn.FORMULATEXT(L35) -> =L32-L34
D37: EBITA Margin | E37: $'m | I37: =I19/I12 -> 0.12222535 | J37: =J19/J12 -> 0.11867677 | K37: =K19/K12 -> 0.10224068 | L37: =L19/L12 -> 0.10968335 | M37: =M19/M12 -> 0.10353924 | N37: =N19/N12 -> 0.097337403 | O37: =O19/O12 -> 0.067509181 | P37: =P19/P12 -> 0.049044017 | Q37: =_xlfn.FORMULATEXT(L37) -> =L19/L12
C38: Dupont Analysis
D39: ROE | E39: $'m | I39: =I32/I115 -> -7.0602748 | J39: =J32/J115 -> -11.362012 | K39: =K32/K115 -> -16.730231 | L39: =L32/L115 -> 5.0027618 | M39: =M32/M115 -> 0.69737317 | N39: =N32/N115 -> 0.34180084 | O39: =O32/O115 -> 0.06401885 | P39: =P32/P115 -> -0.083271133 | Q39: =_xlfn.FORMULATEXT(L39) -> =L32/L115
D40: Net Profit Margin | E40: $'m | I40: =I32/I12 -> 0.091387245 | J40: =J32/J12 -> 0.090220444 | K40: =K32/K12 -> 0.068734984 | L40: =L32/L12 -> 0.044495702 | M40: =M32/M12 -> 0.039567261 | N40: =N32/N12 -> 0.032584613 | O40: =O32/O12 -> 0.0073797396 | P40: =P32/P12 -> -0.0096601378 | Q40: =_xlfn.FORMULATEXT(L40) -> =L32/L12
D41: Asset Turnover | E41: $'m | I41: =I12/I95 -> 1.6492862 | J41: =J12/J95 -> 1.203334 | K41: =K12/K95 -> 1.3603963 | L41: =L12/L95 -> 1.6604926 | M41: =M12/M95 -> 1.5787388 | N41: =N12/N95 -> 1.5068242 | O41: =O12/O95 -> 1.4184588 | P41: =P12/P95 -> 1.3643265 | Q41: =_xlfn.FORMULATEXT(L41) -> =L12/L95
D42: Financial Leverage | E42: $'m | I42: =I95/I115 -> -46.842492 | J42: =J95/J115 -> -104.656 | K42: =K95/K115 -> -178.91991 | L42: =L95/L115 -> 67.710314 | M42: =M95/M115 -> 11.163978 | N42: =N95/N115 -> 6.9614221 | O42: =O95/O115 -> 6.1157553 | P42: =P95/P115 -> 6.3181922 | Q42: =_xlfn.FORMULATEXT(L42) -> =L95/L115
B45: Cash Flow Statement
C47: =Hist!B48 -> Operating Activities
D48: =Hist!C49 -> Net Income | E48: $'m | I48: =Hist!G49 -> 59.9 | J48: =Hist!H49 -> 70.2 | K48: =Hist!I49 -> 51.6 | L48: =L32 -> 175.01214 | M48: =M32 -> 159.86359 | N48: =N32 -> 135.24174 | O48: =O32 -> 30.408067 | P48: =P32 -> -40.202446 | Q48: =_xlfn.FORMULATEXT(L48) -> =L32
D49: =Hist!C50 -> Depreciation | E49: $'m | I49: =Hist!G50 -> 95.1 | J49: =Hist!H50 -> 113.2 | K49: =Hist!I50 -> 126.2 | L49: =L21 -> 121.81333 | M49: =M21 -> 141.64667 | N49: =N21 -> 163.14667 | O49: =O21 -> 185.48 | P49: =P21 -> 207.81333 | Q49: =_xlfn.FORMULATEXT(L49) -> =L21
D50: =Hist!C51 -> Deferred Income Taxes | E50: $'m | I50: =Hist!G51 -> 16.9 | J50: =Hist!H51 -> 31.7 | K50: =Hist!I51 -> 24 | L50: =L29 -> -6 | M50: =M29 -> -6 | N50: =N29 -> -6 | O50: =O29 -> -6 | P50: =P29 -> -6 | Q50: =_xlfn.FORMULATEXT(L50) -> =L29
D51: =Hist!C52 -> Changes in Working Capital | E51: $'m | I51: =Hist!G52 -> -119 | J51: =Hist!H52 -> -4.5 | K51: =Hist!I52 -> -83.8 | L51: =L252 -> -3.9549074 | M51: =M252 -> -2.6349748 | N51: =N252 -> -2.6610987 | O51: =O252 -> 7.3344463 | P51: =P252 -> 1.9007807 | Q51: =_xlfn.FORMULATEXT(L51) -> =L252
D52: Goodwiill Addition/(Impairement) | E52: $'m | L52: =-Inp!L140 -> 0 | M52: =-Inp!M140 -> 0 | N52: =-Inp!N140 -> 0 | O52: =-Inp!O140 -> 0 | P52: =-Inp!P140 -> 0 | Q52: =_xlfn.FORMULATEXT(L52) -> =-Inp!L140
D53: =Hist!C53 -> Other | E53: $'m | I53: =Hist!G53 -> 161.9 | J53: =Hist!H53 -> 164.2 | K53: =Hist!I53 -> 242.1 | L53: =-Inp!L142 -> 0 | M53: =-Inp!M142 -> 0 | N53: =-Inp!N142 -> 0 | O53: =-Inp!O142 -> 0 | P53: =-Inp!P142 -> 0 | Q53: =_xlfn.FORMULATEXT(L53) -> =-Inp!L142
D54: =Hist!C54 -> Operating Cash Flow | E54: $'m | I54: =SUM(I48:I53) -> 214.8 | J54: =SUM(J48:J53) -> 374.8 | K54: =SUM(K48:K53) -> 360.1 | L54: =SUM(L48:L53) -> 286.87057 | M54: =SUM(M48:M53) -> 292.87529 | N54: =SUM(N48:N53) -> 289.72731 | O54: =SUM(O48:O53) -> 217.22251 | P54: =SUM(P48:P53) -> 163.51167 | Q54: =_xlfn.FORMULATEXT(L54) -> =SUM(L48:L53)
C56: =Hist!B57 -> Investing Activities
D57: =Hist!C58 -> CAPEX | E57: $'m | I57: =Hist!G58 -> -134.4 | J57: =Hist!H58 -> -158.7 | K57: =Hist!I58 -> -194.1 | L57: =-L167 -> -225 | M57: =-M167 -> -250 | N57: =-N167 -> -275 | O57: =-O167 -> -275 | P57: =-P167 -> -275 | Q57: =_xlfn.FORMULATEXT(L57) -> =-L167
D58: Intangible Assets | E58: $'m | I58: =Hist!G60 -> -14.9 | J58: =Hist!H60 -> -11.3 | K58: =Hist!I60 -> -15.4 | L58: =-L185 -> -40 | M58: =-M185 -> -40 | N58: =-N185 -> -40 | O58: =-O185 -> -40 | P58: =-P185 -> -40 | Q58: =_xlfn.FORMULATEXT(L58) -> =-L185
D59: =Hist!C60 -> Other | E59: $'m | I59: =Hist!G60 -> -14.9 | J59: =Hist!H60 -> -11.3 | K59: =Hist!I60 -> -15.4 | L59: =-Inp!L143 -> 0 | M59: =-Inp!M143 -> 0 | N59: =-Inp!N143 -> 0 | O59: =-Inp!O143 -> 0 | P59: =-Inp!P143 -> 0 | Q59: =_xlfn.FORMULATEXT(L59) -> =-Inp!L143
D60: =Hist!C61 -> Investing Cash Flow | E60: $'m | I60: =SUM(I57:I59) -> -164.2 | J60: =SUM(J57:J59) -> -181.3 | K60: =SUM(K57:K59) -> -224.9 | L60: =SUM(L57:L59) -> -265 | M60: =SUM(M57:M59) -> -290 | N60: =SUM(N57:N59) -> -315 | O60: =SUM(O57:O59) -> -315 | P60: =SUM(P57:P59) -> -315 | Q60: =_xlfn.FORMULATEXT(L60) -> =SUM(L57:L59)
C62: =Hist!B64 -> Financing Activities
D63: =Hist!C65 -> Revolver Issuance / (Repayment) | E63: $'m | I63: =Hist!G65 -> 10.3 | J63: =Hist!H65 -> 589.5 | K63: =Hist!I65 -> -200 | L63: =L332 -> -355.94153 | M63: =M332 -> 137.73461 | N63: =N332 -> 169.07713 | O63: =O332 -> 223.8735 | P63: =P332 -> 278.48233 | Q63: =_xlfn.FORMULATEXT(L63) -> =L332
D64: =Hist!C66 -> Variable Rate Long Term Debt Issue / (Repayment) | E64: $'m | I64: =Hist!G66 -> 0 | J64: =Hist!H66 -> 0 | K64: =Hist!I66 -> 0 | L64: =-L308 -> -25 | M64: =-M308 -> -25 | N64: =-N308 -> -25 | O64: =-O308 -> -25 | P64: =-P308 -> -25 | Q64: =_xlfn.FORMULATEXT(L64) -> =-L308
D65: =Hist!C67 -> Fixed Rate Long Term Debt Issue / (Repayment) | E65: $'m | I65: =Hist!G67 -> -259.3 | J65: =Hist!H67 -> 4.7 | K65: =Hist!I67 -> -10 | L65: =-L301 -> -150 | M65: =-M301 -> -150 | N65: =-N301 -> -150 | O65: =-O301 -> -150 | P65: =-P301 -> -150 | Q65: =_xlfn.FORMULATEXT(L65) -> =-L301
D66: =Hist!C68 -> Preferred Share Issuance/ (Buy-Back) | E66: $'m | I66: =Hist!G68 -> 0 | J66: =Hist!H68 -> 0 | K66: =Hist!I68 -> 0 | L66: =L273 -> 0 | M66: =M273 -> 120 | N66: =N273 -> 100 | O66: =O273 -> 100 | P66: =P273 -> 100 | Q66: =_xlfn.FORMULATEXT(L66) -> =L273
D67: =Hist!C69 -> Common Share Issuance/ (Buy-Back) | E67: $'m | I67: =Hist!G69 -> 300.2 | J67: =Hist!H69 -> 0.5 | K67: =Hist!I69 -> -94 | L67: =L264 -> -80 | M67: =M264 -> -40 | N67: =N264 -> -20 | O67: =O264 -> -20 | P67: =P264 -> -20 | Q67: =_xlfn.FORMULATEXT(L67) -> =L264
D68: =Hist!C70 -> Preferred Share Dividends | E68: $'m | I68: =Hist!G70 -> -0.544 | J68: =Hist!H70 -> -0.544 | K68: =Hist!I70 -> -0.544 | L68: =-L279 -> -0.544 | M68: =-M279 -> -5.644 | N68: =-N279 -> -14.994 | O68: =-O279 -> -23.494 | P68: =-P279 -> -31.994 | Q68: =_xlfn.FORMULATEXT(L68) -> =-L279
D69: =Hist!C71 -> Common Share Dividends | E69: $'m | I69: =Hist!G71 -> -483 | J69: =Hist!H71 -> 0 | K69: =Hist!I71 -> 0 | L69: =-L269 -> -43.753035 | M69: =-M269 -> -39.965899 | N69: =-N269 -> -33.810435 | O69: =-O269 -> -7.6020168 | P69: =-P269 -> 0 | Q69: =_xlfn.FORMULATEXT(L69) -> =-L269
D70: =Hist!C72 -> Other | E70: $'m | I70: =Hist!G72 -> -102.7 | J70: =Hist!H72 -> -46.3 | K70: =Hist!I72 -> -54.1 | L70: =Inp!L141+Inp!L144 -> 0 | M70: =Inp!M141+Inp!M144 -> 0 | N70: =Inp!N141+Inp!N144 -> 0 | O70: =Inp!O141+Inp!O144 -> 0 | P70: =Inp!P141+Inp!P144 -> 0 | Q70: =_xlfn.FORMULATEXT(L70) -> =Inp!L141+Inp!L144
D71: =Hist!C73 -> Financing Cash Flow | E71: $'m | I71: =SUM(I63:I70) -> -535.044 | J71: =SUM(J63:J70) -> 547.856 | K71: =SUM(K63:K70) -> -358.644 | L71: =SUM(L63:L70) -> -655.23857 | M71: =SUM(M63:M70) -> -2.8752865 | N71: =SUM(N63:N70) -> 25.272693 | O71: =SUM(O63:O70) -> 97.777486 | P71: =SUM(P63:P70) -> 151.48833 | Q71: =_xlfn.FORMULATEXT(L71) -> =SUM(L63:L70)
D73: =Hist!C75 -> Change in Cash Position | E73: $'m | I73: =SUM(I71,I60,I54) -> -484.444 | J73: =SUM(J71,J60,J54) -> 741.356 | K73: =SUM(K71,K60,K54) -> -223.444 | L73: =SUM(L71,L60,L54) -> -633.368 | M73: =SUM(M71,M60,M54) -> 0 | N73: =SUM(N71,N60,N54) -> 0 | O73: =SUM(O71,O60,O54) -> 0 | P73: =SUM(P71,P60,P54) -> 0 | Q73: =_xlfn.FORMULATEXT(L73) -> =SUM(L71,L60,L54)
D74: =Hist!C76 -> Beginning Cash | E74: $'m | I74: =Hist!G76 -> 542.4 | J74: =Hist!H76 -> 74.856 | K74: =Hist!I76 -> 830.912 | L74: =K75 -> 633.368 | M74: =L75 -> 0 | N74: =M75 -> 0 | O74: =N75 -> 0 | P74: =O75 -> 0 | Q74: =_xlfn.FORMULATEXT(L74) -> =K75
D75: =Hist!C77 -> Ending Cash | E75: $'m | I75: =Hist!G77 -> 74.856 | J75: =Hist!H77 -> 830.912 | K75: =Hist!I77 -> 633.368 | L75: =SUM(L73:L74) -> 0 | M75: =SUM(M73:M74) -> 0 | N75: =SUM(N73:N74) -> 0 | O75: =SUM(O73:O74) -> 0 | P75: =SUM(P73:P74) -> 0 | Q75: =_xlfn.FORMULATEXT(L75) -> =SUM(L73:L74)
B79: Balance Sheet
C81: =Hist!B87 -> ASSETS
D82: =Hist!C88 -> Cash and Equivalents | E82: $'m | I82: =Hist!G88 -> 74.856 | J82: =Hist!H88 -> 830.912 | K82: =Hist!I88 -> 633.368 | L82: =L75 -> 0 | M82: =M75 -> 0 | N82: =N75 -> 0 | O82: =O75 -> 0 | P82: =P75 -> 0 | Q82: =_xlfn.FORMULATEXT(L82) -> =L75
D83: =Hist!C89 -> Accounts Receivable | E83: $'m | I83: =Hist!G89 -> 266.6 | J83: =Hist!H89 -> 306.8 | K83: =Hist!I89 -> 308.4 | L83: =L243 -> 317.89175 | M83: =M243 -> 326.54477 | N83: =N243 -> 335.44964 | O83: =O243 -> 332.11517 | P83: =P243 -> 336.35532 | Q83: =_xlfn.FORMULATEXT(L83) -> =L243
D84: =Hist!C90 -> Inventory | E84: $'m | I84: =Hist!G90 -> 532.7 | J84: =Hist!H90 -> 630.2 | K84: =Hist!I90 -> 685.9 | L84: =L244 -> 711.82019 | M84: =M244 -> 736.89538 | N84: =N244 -> 762.91109 | O84: =O244 -> 779.57763 | P84: =P244 -> 805.16487 | Q84: =_xlfn.FORMULATEXT(L84) -> =L244
D85: =Hist!C91 -> Other | E85: $'m | I85: =Hist!G91 -> 51.4 | J85: =Hist!H91 -> 61 | K85: =Hist!I91 -> 65.3 | L85: =L245 -> 68.018374 | M85: =M245 -> 70.414448 | N85: =N245 -> 72.900393 | O85: =O245 -> 74.492974 | P85: =P245 -> 76.937976 | Q85: =_xlfn.FORMULATEXT(L85) -> =L245
D86: =Hist!C92 -> Total Current Assets | E86: $'m | I86: =SUM(I82:I85) -> 925.556 | J86: =SUM(J82:J85) -> 1828.912 | K86: =SUM(K82:K85) -> 1692.968 | L86: =SUM(L82:L85) -> 1097.7303 | M86: =SUM(M82:M85) -> 1133.8546 | N86: =SUM(N82:N85) -> 1171.2611 | O86: =SUM(O82:O85) -> 1186.1858 | P86: =SUM(P82:P85) -> 1218.4582 | Q86: =_xlfn.FORMULATEXT(L86) -> =SUM(L82:L85)
D88: =Hist!C94 -> Net PP&E | E88: $'m | I88: =Hist!G94 -> 515.3 | J88: =Hist!H94 -> 586.9 | K88: =Hist!I94 -> 636.6 | L88: =L206 -> 783.36667 | M88: =M206 -> 939.3 | N88: =N206 -> 1102.7333 | O88: =O206 -> 1247.8333 | P88: =P206 -> 1374.6 | Q88: =_xlfn.FORMULATEXT(L88) -> =L206
D89: =Hist!C95 -> Goodwill | E89: $'m | I89: =Hist!G95 -> 116 | J89: =Hist!H95 -> 115.9 | K89: =Hist!I95 -> 116 | L89: =K89+Inp!L140 -> 116 | M89: =L89+Inp!M140 -> 116 | N89: =M89+Inp!N140 -> 116 | O89: =N89+Inp!O140 -> 116 | P89: =O89+Inp!P140 -> 116 | Q89: =_xlfn.FORMULATEXT(L89) -> =K89+Inp!L140
D90: =Hist!C96 -> Intangibles | E90: $'m | I90: =Hist!G96 -> 219.9 | J90: =Hist!H96 -> 220.6 | K90: =Hist!I96 -> 207.9 | L90: =L212 -> 204.32 | M90: =M212 -> 196.74 | N90: =N212 -> 185.16 | O90: =O212 -> 169.58 | P90: =P212 -> 150 | Q90: =_xlfn.FORMULATEXT(L90) -> =L212
D91: =Hist!C97 -> Deferred income taxes | E91: $'m | I91: =Hist!G97 -> 14 | J91: =Hist!H97 -> 17.7 | K91: =Hist!I97 -> 28.8 | L91: =K91+L229 -> 34.8 | M91: =L91+M229 -> 40.8 | N91: =M91+N229 -> 46.8 | O91: =N91+O229 -> 52.8 | P91: =O91+P229 -> 58.8 | Q91: =_xlfn.FORMULATEXT(L91) -> =K91+L229
D92: =Hist!C98 -> Other | E92: $'m | I92: =Hist!G98 -> 145.9 | J92: =Hist!H98 -> 159.1 | K92: =Hist!I98 -> 132.5 | L92: =K92+Inp!L143 -> 132.5 | M92: =L92+Inp!M143 -> 132.5 | N92: =M92+Inp!N143 -> 132.5 | O92: =N92+Inp!O143 -> 132.5 | P92: =O92+Inp!P143 -> 132.5 | Q92: =_xlfn.FORMULATEXT(L92) -> =K92+Inp!L143
D93: =Hist!C99 -> Total Long Term Assets | E93: $'m | I93: =SUM(I88:I92) -> 1011.1 | J93: =SUM(J88:J92) -> 1100.2 | K93: =SUM(K88:K92) -> 1121.8 | L93: =SUM(L88:L92) -> 1270.9867 | M93: =SUM(M88:M92) -> 1425.34 | N93: =SUM(N88:N92) -> 1583.1933 | O93: =SUM(O88:O92) -> 1718.7133 | P93: =SUM(P88:P92) -> 1831.9 | Q93: =_xlfn.FORMULATEXT(L93) -> =SUM(L88:L92)
D95: =Hist!C101 -> Total Assets | E95: $'m | I95: =I86+I93 -> 1936.656 | J95: =J86+J93 -> 2929.112 | K95: =K86+K93 -> 2814.768 | L95: =L86+L93 -> 2368.717 | M95: =M86+M93 -> 2559.1946 | N95: =N86+N93 -> 2754.4545 | O95: =O86+O93 -> 2904.8991 | P95: =P86+P93 -> 3050.3582 | Q95: =_xlfn.FORMULATEXT(L95) -> =L86+L93
C98: =Hist!B104 -> LIABILITIES AND EQUITY
D99: =Hist!C105 -> Bank Debt - Revolver | E99: $'m | I99: =Hist!G105 -> 10.5 | J99: =Hist!H105 -> 600 | K99: =Hist!I105 -> 400 | L99: =L333 -> 44.05847 | M99: =M333 -> 181.79308 | N99: =N333 -> 350.87021 | O99: =O333 -> 574.74371 | P99: =P333 -> 853.22604 | Q99: =_xlfn.FORMULATEXT(L99) -> =L333
D100: =Hist!C106 -> Accounts Payable | E100: $'m | I100: =Hist!G106 -> 547 | J100: =Hist!H106 -> 678.4 | K100: =Hist!I106 -> 650.3 | L100: =L247 -> 674.64736 | M100: =M247 -> 698.41307 | N100: =N247 -> 723.07018 | O100: =O247 -> 738.86636 | P100: =P247 -> 763.11737 | Q100: =_xlfn.FORMULATEXT(L100) -> =L247
D101: =Hist!C107 -> Other | E101: $'m | I101: =Hist!G107 -> 206.6 | J101: =Hist!H107 -> 248.5 | K101: =Hist!I107 -> 266.2 | L101: =L248 -> 276.02805 | M101: =M248 -> 285.75165 | N101: =N248 -> 295.83997 | O101: =O248 -> 302.30288 | P101: =P248 -> 312.22504 | Q101: =_xlfn.FORMULATEXT(L101) -> =L248
D102: =Hist!C108 -> Total Current Liabilities | E102: $'m | I102: =SUM(I99:I101) -> 764.1 | J102: =SUM(J99:J101) -> 1526.9 | K102: =SUM(K99:K101) -> 1316.5 | L102: =SUM(L99:L101) -> 994.73388 | M102: =SUM(M99:M101) -> 1165.9578 | N102: =SUM(N99:N101) -> 1369.7804 | O102: =SUM(O99:O101) -> 1615.913 | P102: =SUM(P99:P101) -> 1928.5685 | Q102: =_xlfn.FORMULATEXT(L102) -> =SUM(L99:L101)
D104: =Hist!C110 -> Variable Rate Long Term Debt | E104: $'m | I104: =Hist!G110 -> 0 | J104: =Hist!H110 -> 0 | K104: =Hist!I110 -> 250 | L104: =L309 -> 225 | M104: =M309 -> 200 | N104: =N309 -> 175 | O104: =O309 -> 150 | P104: =P309 -> 125 | Q104: =_xlfn.FORMULATEXT(L104) -> =L309
D105: =Hist!C111 -> Fixed Rate Long Term Debt | E105: $'m | I105: =Hist!G111 -> 889.9 | J105: =Hist!H111 -> 1035.5 | K105: =Hist!I111 -> 896.6 | L105: =L302 -> 746.6 | M105: =M302 -> 596.6 | N105: =N302 -> 446.6 | O105: =O302 -> 296.6 | P105: =P302 -> 146.6 | Q105: =_xlfn.FORMULATEXT(L105) -> =L302
D106: =Hist!C112 -> Other | E106: $'m | I106: =Hist!G112 -> 324 | J106: =Hist!H112 -> 394.7 | K106: =Hist!I112 -> 367.4 | L106: =K106+Inp!L144 -> 367.4 | M106: =L106+Inp!M144 -> 367.4 | N106: =M106+Inp!N144 -> 367.4 | O106: =N106+Inp!O144 -> 367.4 | P106: =O106+Inp!P144 -> 367.4 | Q106: =_xlfn.FORMULATEXT(L106) -> =K106+Inp!L144
D107: =Hist!C113 -> Total Long Term Liabilities | E107: $'m | I107: =SUM(I104:I106) -> 1213.9 | J107: =SUM(J104:J106) -> 1430.2 | K107: =SUM(K104:K106) -> 1514 | L107: =SUM(L104:L106) -> 1339 | M107: =SUM(M104:M106) -> 1164 | N107: =SUM(N104:N106) -> 989 | O107: =SUM(O104:O106) -> 814 | P107: =SUM(P104:P106) -> 639 | Q107: =_xlfn.FORMULATEXT(L107) -> =SUM(L104:L106)
D109: =Hist!C115 -> Total Liabilities | E109: $'m | I109: =I102+I107 -> 1978 | J109: =J102+J107 -> 2957.1 | K109: =K102+K107 -> 2830.5 | L109: =L102+L107 -> 2333.7339 | M109: =M102+M107 -> 2329.9578 | N109: =N102+N107 -> 2358.7804 | O109: =O102+O107 -> 2429.913 | P109: =P102+P107 -> 2567.5685 | Q109: =_xlfn.FORMULATEXT(L109) -> =L102+L107
D111: =Hist!C117 -> Preferred Shares | E111: $'m | I111: =Hist!G117 -> 6.4 | J111: =Hist!H117 -> 6.4 | K111: =Hist!I117 -> 6.4 | L111: =L274 -> 6.4 | M111: =M274 -> 126.4 | N111: =N274 -> 226.4 | O111: =O274 -> 326.4 | P111: =P274 -> 426.4 | Q111: =_xlfn.FORMULATEXT(L111) -> =L274
D112: =Hist!C118 -> Common Shares | E112: $'m | I112: =Hist!G118 -> 365.3 | J112: =Hist!H118 -> 371.9 | K112: =Hist!I118 -> 346.4 | L112: =L265 -> 266.4 | M112: =M265 -> 226.4 | N112: =N265 -> 206.4 | O112: =O265 -> 186.4 | P112: =P265 -> 166.4 | Q112: =_xlfn.FORMULATEXT(L112) -> =L265
D113: =Hist!C119 -> Retained Earnings | E113: $'m | I113: =Hist!G119 -> -429.244 | J113: =Hist!H119 -> -419.888 | K113: =Hist!I119 -> -395.232 | L113: =L285 -> -264.5169 | M113: =M285 -> -150.2632 | N113: =N285 -> -63.825895 | O113: =O285 -> -64.513845 | P113: =P285 -> -136.71029 | Q113: =_xlfn.FORMULATEXT(L113) -> =L285
D114: =Hist!C120 -> Other | E114: $'m | I114: =Hist!G120 -> 16.2 | J114: =Hist!H120 -> 13.6 | K114: =Hist!I120 -> 26.7 | L114: =K114+Inp!L141 -> 26.7 | M114: =L114+Inp!M141 -> 26.7 | N114: =M114+Inp!N141 -> 26.7 | O114: =N114+Inp!O141 -> 26.7 | P114: =O114+Inp!P141 -> 26.7 | Q114: =_xlfn.FORMULATEXT(L114) -> =K114+Inp!L141
D115: =Hist!C121 -> Shareholder's Equity | E115: $'m | I115: =SUM(I111:I114) -> -41.344 | J115: =SUM(J111:J114) -> -27.988 | K115: =SUM(K111:K114) -> -15.732 | L115: =SUM(L111:L114) -> 34.983104 | M115: =SUM(M111:M114) -> 229.2368 | N115: =SUM(N111:N114) -> 395.67411 | O115: =SUM(O111:O114) -> 474.98616 | P115: =SUM(P111:P114) -> 482.78971 | Q115: =_xlfn.FORMULATEXT(L115) -> =SUM(L111:L114)
C117: =Hist!B123 -> Total Liabilities and Equity | I117: =I109+I115 -> 1936.656 | J117: =J109+J115 -> 2929.112 | K117: =K109+K115 -> 2814.768 | L117: =L109+L115 -> 2368.717 | M117: =M109+M115 -> 2559.1946 | N117: =N109+N115 -> 2754.4545 | O117: =O109+O115 -> 2904.8991 | P117: =P109+P115 -> 3050.3582 | Q117: =_xlfn.FORMULATEXT(L117) -> =L109+L115
D119: Accuracy Check | F119: =ROUND(SUM(I119:P119),4) -> 0 | I119: =I117-I95 -> 0 | J119: =J117-J95 -> 0 | K119: =K117-K95 -> 0 | L119: =L117-L95 -> 0 | M119: =M117-M95 -> 0 | N119: =N117-N95 -> 0 | O119: =O117-O95 -> 0 | P119: =P117-P95 -> 0 | Q119: =_xlfn.FORMULATEXT(L119) -> =L117-L95
A122: SCHEDULES & CALCULATIONS
B124: Revenue Schedule
D126: Core Business: Sales Price inflation Rate | E126: % | L126: =Inp!L37 -> 0.01 | M126: =Inp!M37 -> 0.01 | N126: =Inp!N37 -> 0.01 | O126: =Inp!O37 -> 0.01 | P126: =Inp!P37 -> 0.01 | Q126: =_xlfn.FORMULATEXT(L126) -> =Inp!L37
D127: Auxiliary Business: Sales Growth Rate | E127: % | L127: =Inp!L39 -> 0.01 | M127: =Inp!M39 -> 0.01 | N127: =Inp!N39 -> 0.01 | O127: =Inp!O39 -> 0.01 | P127: =Inp!P39 -> 0.01 | Q127: =_xlfn.FORMULATEXT(L127) -> =Inp!L39
C129: Core Business
D131: Volume: New Devices | E131: units | K131: =Inp!K41 -> 230747.96 | L131: =Inp!L41 -> 235362.92 | M131: =Inp!M41 -> 240070.18 | N131: =Inp!N41 -> 244871.58 | O131: =Inp!O41 -> 249769.01 | P131: =Inp!P41 -> 254764.39 | Q131: =_xlfn.FORMULATEXT(L131) -> =Inp!L41
D132: =Inp!D35 -> Volume capacity | E132: units | L132: =Inp!L35 -> 260000 | M132: =Inp!M35 -> 260000 | N132: =Inp!N35 -> 260000 | O132: =Inp!O35 -> 240000 | P132: =Inp!P35 -> 240000 | Q132: =_xlfn.FORMULATEXT(L132) -> =Inp!L35
D134: Actual Volume: New Devices | E134: units | L134: =MIN(L131,L132) -> 235362.92 | M134: =MIN(M131,M132) -> 240070.18 | N134: =MIN(N131,N132) -> 244871.58 | O134: =MIN(O131,O132) -> 240000 | P134: =MIN(P131,P132) -> 240000 | Q134: =_xlfn.FORMULATEXT(L134) -> =MIN(L131,L132)
D135: Gross Sales Price per sqm | E135: $/sqm | K135: =Inp!K33 -> 14105 | L135: =K135*(1+L126) -> 14246.05 | M135: =L135*(1+M126) -> 14388.51 | N135: =M135*(1+N126) -> 14532.396 | O135: =N135*(1+O126) -> 14677.72 | P135: =O135*(1+P126) -> 14824.497 | Q135: =_xlfn.FORMULATEXT(L135) -> =K135*(1+L126)
C137: Auxillary Revenue | E137: $'m | K137: =Inp!K31 -> 574.5 | L137: =K137*(1+L127) -> 580.245 | M137: =L137*(1+M127) -> 586.04745 | N137: =M137*(1+N127) -> 591.90792 | O137: =N137*(1+O127) -> 597.827 | P137: =O137*(1+P127) -> 603.80527 | Q137: =_xlfn.FORMULATEXT(L137) -> =K137*(1+L127)
C139: Revenue
D141: Core Revenue | E141: $'m | K141: =K135*K131/million -> 3254.7 | L141: =L135*L134/million -> 3352.9919 | M141: =M135*M134/million -> 3454.2523 | N141: =N135*N134/million -> 3558.5707 | O141: =O135*O134/million -> 3522.6527 | P141: =P135*P134/million -> 3557.8792 | Q141: =_xlfn.FORMULATEXT(L141) -> =L135*L134/million
D142: Auxillary Revenue | E142: $'m | K142: =K137 -> 574.5 | L142: =L137 -> 580.245 | M142: =M137 -> 586.04745 | N142: =N137 -> 591.90792 | O142: =O137 -> 597.827 | P142: =P137 -> 603.80527 | Q142: =_xlfn.FORMULATEXT(L142) -> =L137
...
